kcc/__init__.py
kcc/cli.py
kcc/defaults.py
kcc/kconfig.py
kcc/query.py
kcc/version.py
kcc-0.0.8.dist-info/METADATA
kcc-0.0.8.dist-info/RECORD
kcc-0.0.8.dist-info/WHEEL
kcc-0.0.8.dist-info/entry_points.txt
kcc-0.0.8.dist-info/top_level.txt
