Metadata-Version: 2.1
Name: kcc
Version: 0.0.8
Summary: Check kernel config for security issues
Home-page: https://github.com/clearlinux/kernel-config-checker
Author: Arjan van de Ven
Author-email: arjan@linux.intel.com
License: GPL-3.0
Platform: UNKNOWN
Classifier: Development Status :: 4 - Beta
Classifier: Intended Audience :: Developers
Classifier: License :: OSI Approved :: GNU General Public License v3 (GPLv3)
Classifier: Natural Language :: English
Classifier: Operating System :: OS Independent
Classifier: Programming Language :: Python :: 3.6
Classifier: Programming Language :: Python :: 3.7
Classifier: Programming Language :: Python :: Implementation :: CPython
Classifier: Programming Language :: Python :: Implementation :: PyPy
